py4ai/data/__init__.py
py4ai/data/_version.py
py4ai/data/exceptions.py
py4ai/data/py.typed
py4ai/data/datasets/__init__.py
py4ai/data/datasets/data/unbalanced_features.p
py4ai/data/datasets/data/unbalanced_labels.p
py4ai/data/datasets/data/weather_nyc_short.csv
py4ai/data/layer/__init__.py
py4ai/data/layer/common/__init__.py
py4ai/data/layer/common/criteria.py
py4ai/data/layer/common/repository.py
py4ai/data/layer/common/serialiazer.py
py4ai/data/layer/fs/__init__.py
py4ai/data/layer/fs/criteria.py
py4ai/data/layer/fs/repository.py
py4ai/data/layer/fs/serializer.py
py4ai/data/layer/fs/tables.py
py4ai/data/layer/mongo/__init__.py
py4ai/data/layer/mongo/criteria.py
py4ai/data/layer/mongo/repository.py
py4ai/data/layer/mongo/serializer.py
py4ai/data/layer/pandas/__init__.py
py4ai/data/layer/pandas/criteria.py
py4ai/data/layer/pandas/repository.py
py4ai/data/layer/sqlalchemy/__init__.py
py4ai/data/layer/sqlalchemy/criteria.py
py4ai/data/layer/sqlalchemy/repository.py
py4ai/data/layer/sqlalchemy/serializer.py
py4ai/data/model/__init__.py
py4ai/data/model/core.py
py4ai/data/model/ml.py
py4ai/data/model/text.py
requirements/requirements.in
py4ai_data-0.0.1.dist-info/LICENSE
py4ai_data-0.0.1.dist-info/METADATA
py4ai_data-0.0.1.dist-info/WHEEL
py4ai_data-0.0.1.dist-info/top_level.txt
py4ai_data-0.0.1.dist-info/RECORD
